evm_py/__init__.py
evm_py/async_http.py
evm_py/const.py
evm_py/evm_account.py
evm_py/file.py
evm_py/network.py
evm_py/proxy.py
evm_py/util.py
evm_py/version.py
evm_python-0.1.6.dist-info/licenses/LICENSE
evm_python-0.1.6.dist-info/METADATA
evm_python-0.1.6.dist-info/WHEEL
evm_python-0.1.6.dist-info/top_level.txt
evm_python-0.1.6.dist-info/RECORD
