Metadata-Version: 2.4
Name: evm_python
Version: 0.1.6
Summary: evm python package
Home-page: https://github.com/zefzhou/evm_py
Author: zefzhou44
Author-email: zefzhou44@gmail.com
Classifier: Programming Language :: Python :: 3
Classifier: License :: OSI Approved :: MIT License
Classifier: Operating System :: OS Independent
Requires-Python: >=3.8.0
License-File: LICENSE
Requires-Dist: bip44==0.1.5
Requires-Dist: eth_typing>=5.2.1
Requires-Dist: eth_utils>=5.3.0
Requires-Dist: loguru>=0.7.2
Requires-Dist: Requests>=2.32.3
Requires-Dist: web3>=7.11.0
Requires-Dist: aiohttp-socks>=0.10.1
Requires-Dist: python-socks>=2.7.1
Requires-Dist: aiohttp>=3.11.18
Dynamic: author
Dynamic: author-email
Dynamic: classifier
Dynamic: description
Dynamic: description-content-type
Dynamic: home-page
Dynamic: license-file
Dynamic: requires-dist
Dynamic: requires-python
Dynamic: summary
